cosmotech_api/__init__.py
cosmotech_api/api_client.py
cosmotech_api/api_response.py
cosmotech_api/configuration.py
cosmotech_api/exceptions.py
cosmotech_api/model_utils.py
cosmotech_api/py.typed
cosmotech_api/rest.py
cosmotech_api/api/__init__.py
cosmotech_api/api/connector_api.py
cosmotech_api/api/dataset_api.py
cosmotech_api/api/meta_api.py
cosmotech_api/api/organization_api.py
cosmotech_api/api/run_api.py
cosmotech_api/api/runner_api.py
cosmotech_api/api/scenario_api.py
cosmotech_api/api/scenariorun_api.py
cosmotech_api/api/scenariorunresult_api.py
cosmotech_api/api/solution_api.py
cosmotech_api/api/twingraph_api.py
cosmotech_api/api/user_api.py
cosmotech_api/api/validator_api.py
cosmotech_api/api/workspace_api.py
cosmotech_api/apis/__init__.py
cosmotech_api/model/__init__.py
cosmotech_api/model/component_role_permissions.py
cosmotech_api/model/connector.py
cosmotech_api/model/connector_parameter.py
cosmotech_api/model/connector_parameter_group.py
cosmotech_api/model/container_resource_size_info.py
cosmotech_api/model/container_resource_sizing.py
cosmotech_api/model/dataset.py
cosmotech_api/model/dataset_access_control.py
cosmotech_api/model/dataset_compatibility.py
cosmotech_api/model/dataset_connector.py
cosmotech_api/model/dataset_copy_parameters.py
cosmotech_api/model/dataset_role.py
cosmotech_api/model/dataset_search.py
cosmotech_api/model/dataset_security.py
cosmotech_api/model/dataset_source_type.py
cosmotech_api/model/dataset_twin_graph_hash.py
cosmotech_api/model/dataset_twin_graph_info.py
cosmotech_api/model/dataset_twin_graph_query.py
cosmotech_api/model/delete_historical_data.py
cosmotech_api/model/file_upload_metadata.py
cosmotech_api/model/file_upload_validation.py
cosmotech_api/model/graph_properties.py
cosmotech_api/model/organization.py
cosmotech_api/model/organization_access_control.py
cosmotech_api/model/organization_role.py
cosmotech_api/model/organization_security.py
cosmotech_api/model/organization_service.py
cosmotech_api-3.3.4.dist-info/LICENSE
cosmotech_api-3.3.4.dist-info/METADATA
cosmotech_api-3.3.4.dist-info/WHEEL
cosmotech_api-3.3.4.dist-info/top_level.txt
cosmotech_api-3.3.4.dist-info/RECORD
