Metadata-Version: 2.2
Name: cosmotech-api
Version: 3.3.4
Summary: Cosmo Tech Platform API
Home-page: 
Author: Repository
Author-email: platform@cosmotech.com
License: MIT License
Keywords: OpenAPI,OpenAPI-Generator,Cosmo Tech Platform API
License-File: LICENSE
Requires-Dist: urllib3<2.1.0,>=1.25.3
Requires-Dist: python-dateutil
Requires-Dist: pydantic>=2
Requires-Dist: typing-extensions>=4.7.1
Dynamic: author
Dynamic: author-email
Dynamic: description
Dynamic: description-content-type
Dynamic: keywords
Dynamic: license
Dynamic: requires-dist
Dynamic: summary
